equimage/__init__.py
equimage/helpers.py
equimage/image.py
equimage/image_colors.py
equimage/image_colorspaces.py
equimage/image_editors.py
equimage/image_filters.py
equimage/image_geometry.py
equimage/image_hdr.py
equimage/image_io.py
equimage/image_masks.py
equimage/image_multiscale.py
equimage/image_skimage.py
equimage/image_stars.py
equimage/image_stats.py
equimage/image_stretch.py
equimage/image_utils.py
equimage/imports.py
equimage/params.py
equimage/stretchfunctions.py
equimage/images/HSVwheel.png
equimagelab/__init__.py
equimagelab/params.py
equimagelab/images/splash.png
equimagelab/jupyter/__init__.py
equimagelab/jupyter/backend_dash.py
equimagelab/jupyter/backend_plotly.py
equimagelab/jupyter/imports.py
equimagelab/jupyter/params.py
equimagelab/jupyter/utils.py
equimagelab/jupyter/assets/equimagelab.css
equimagelab-2.1.0.dist-info/licenses/LICENSE
equimagelab_launcher/__init__.py
equimagelab_launcher/icons/icon.ico
equimagelab_launcher/icons/icon.png
equimagelab_launcher/images/splash.png
equimagelab_launcher/templates/equimagelab.ipynb
equimagelab-2.1.0.dist-info/METADATA
equimagelab-2.1.0.dist-info/WHEEL
equimagelab-2.1.0.dist-info/entry_points.txt
equimagelab-2.1.0.dist-info/top_level.txt
equimagelab-2.1.0.dist-info/RECORD
