Metadata-Version: 2.4
Name: eQuimageLab
Version: 2.1.0
Summary: eQuimageLab is a tool to postprocess astronomical images with JupyterLab notebooks
Author-email: Yann-Michel Niquet <contact@ymniquet.fr>
License-Expression: GPL-3.0-or-later
Project-URL: homepage, https://astro.ymniquet.fr/
Project-URL: documentation, https://astro.ymniquet.fr/codes/equimagelab/docs/
Project-URL: repository, https://github.com/ymniquet/eQuimageLab
Classifier: Programming Language :: Python :: 3
Classifier: Operating System :: OS Independent
Requires-Python: >=3.8
License-File: LICENSE
Requires-Dist: pandas
Requires-Dist: numpy
Requires-Dist: scipy
Requires-Dist: pywavelets
Requires-Dist: pillow
Requires-Dist: tifffile
Requires-Dist: imagecodecs
Requires-Dist: astropy
Requires-Dist: scikit-image
Requires-Dist: dask
Requires-Dist: jupyterlab
Requires-Dist: plotly>=6.0
Requires-Dist: dash>=3.0
Requires-Dist: dash-bootstrap-components>=2.0
Requires-Dist: dash_bootstrap_templates>=2.0
Requires-Dist: dash_extensions
Requires-Dist: tk
Dynamic: license-file
